vthread/__init__.py
vthread/test.py
vthread/test2.py
vthread/test3.py
vthread/vthread.py
vthread-0.1.5.dist-info/LICENSE
vthread-0.1.5.dist-info/METADATA
vthread-0.1.5.dist-info/WHEEL
vthread-0.1.5.dist-info/top_level.txt
vthread-0.1.5.dist-info/RECORD
