Metadata-Version: 2.1
Name: vthread
Version: 0.1.5
Summary: the best threadpool pack.
Home-page: https://github.com/cilame/vthread
Author: vilame
Author-email: opaquism@hotmail.com
License: MIT
Platform: UNKNOWN
Classifier: Environment :: Web Environment
Classifier: Intended Audience :: Developers
Classifier: Operating System :: OS Independent
